joe_utils-0.1.1.dist-info/METADATA
joe_utils-0.1.1.dist-info/RECORD
joe_utils-0.1.1.dist-info/WHEEL
joe_utils-0.1.1.dist-info/top_level.txt
joeutils/__init__.py
joeutils/algorithms/__init__.py
joeutils/algorithms/hash/__init__.py
joeutils/algorithms/sorts/__init__.py
joeutils/data_manipulation/__init__.py
joeutils/data_manipulation/functions/__init__.py
joeutils/data_manipulation/maps/__init__.py
joeutils/data_manipulation/sets/__init__.py
joeutils/data_manipulation/string/__init__.py
joeutils/data_structures/__init__.py
joeutils/data_structures/comprehensions/__init__.py
joeutils/data_structures/comprehensions/maps/__init__.py
joeutils/hashing/__init__.py
joeutils/io/__init__.py
joeutils/io/file_io/__init__.py
joeutils/io/yaml_io/__init__.py
joeutils/state_management/__init__.py
joeutils/state_management/state_mgmt.py
joeutils/testing/__init__.py
